Workbook

Sheet README
B2: JHP SEO KEYWORD TRACKER · v2
B3: Jindal Hydro Projects Inc. | 261 keywords | Built 3 Aug 2026
B6: ⚠ READ THIS FIRST
B7: The website problem | C7: As of Aug 2026 JHP has NO owned website. jindalhydro.com redirects to jindalhydraulics.com (an IndiaMART-hosted seller microsite) and jindalhydroprojects.com is a TradeIndia-hosted microsite. Neither can host a blog, custom URLs, or schema markup. Until an owned site exists, blogs cannot be published and rankings cannot be built. See the SEO Strategy document in this folder.
B8: What that means for this file | C8: Every sheet here still applies — the keyword research, priorities and competitor findings are all valid. But the Rank Tracker will stay empty until there is a site to rank. Treat this as the plan you execute the moment the site is live.
B10: SHEETS
B11: Keyword Master | C11: 261 keywords across 14 categories. Intent, market, estimated volume, difficulty, and a computed Priority Score.
B12: Rank Tracker | C12: One row per keyword, 26 dated weekly columns. Enter Google position each Monday.
B13: Traffic & Conversions | C13: Weekly clicks, impressions, CTR, position and enquiries per landing page.
B14: Competitor Audit | C14: 13 competitors audited Aug 2026 — platform, blog depth, URL structure, strengths, weaknesses, threat level.
B15: Content Gaps | C15: 12 topic areas nobody in the Indian market owns, scored by opportunity.
B16: Content Map | C16: Blog-to-keyword mapping. Prevents two posts competing for one term.
B17: Blog Pipeline | C17: Rolling calendar: 2 posts/day Mon-Sat, 1 deep-dive Sunday.
B18: Dashboard | C18: Live metrics from every sheet.
B20: WEEKLY ROUTINE
B21: Monday | C21: Enter Google positions in Rank Tracker (yellow columns). Paste GSC clicks/impressions into Traffic & Conversions.
B22: Any day | C22: Update Content Map status as posts go live.
B23: Monthly | C23: Re-check Competitor Audit — has anyone launched a blog or new product line?
B25: COLOUR CODE
B26: Yellow | C26: You type here.
B27: Blue text | C27: Hardcoded research estimate — replace with live tool data.
B28: Green text | C28: Reference to another sheet.
B29: Black text | C29: Formula.
B31: DATA SOURCES & LIMITS
B32: Search volumes | C32: ESTIMATES. Compiled Aug 2026 from competitor page-one analysis, IndiaMART/TradeIndia category demand and search-suggest patterns. Use for RELATIVE prioritisation only. Replace with Ahrefs, Semrush or Google Keyword Planner data when a tool is connected.
B33: Difficulty (1-100) | C33: ESTIMATE of ranking difficulty from observed page-one competitor strength. Lower = easier. IndiaMART and TradeIndia dominate transactional head terms, which is why difficulty is high there and low on informational and long-tail terms.
B34: Priority Score | C34: FORMULA: (Volume weight x 0.40) + (Ease x 0.35) + (Intent value x 0.25), scaled 0-100.
B35: Competitor audit | C35: Manual audit of live sites, Aug 2026. Blog post counts are approximate — taken from visible pagination.
B36: Connecting live data | C36: Column order matches a standard Google Search Console export, so live position and click data can be pasted or auto-filled once the Ahrefs / GSC connector is authorised.

Sheet Keyword Master
A1: KEYWORD MASTER — 267 KEYWORDS
A2: Blue = hardcoded research estimate (replace with tool data). Priority Score is a formula. Filter by Category or Priority Band.
A4: # | B4: Keyword | C4: Category | D4: Cluster | E4: Intent | F4: Market | G4: Est. Vol/mo (IN) | H4: Est. Vol/mo (Global) | I4: Difficulty | J4: Ease | K4: Intent Value | L4: Priority Score | M4: Priority Band | N4: Target Page / URL
A5: 1 | B5: scrap baling press machine | C5: Balers | D5: Baler head | E5: Transactional | F5: India | G5: 1600 | H5: 2400 | I5: 42 | J5: =100-I5 | K5: 100 | L5: =ROUND((G5/MAX($G$5:$G$271)*100*0.4)+(J5*0.35)+(K5*0.25),1) | M5: =IF(L5>=62,"1 - Do now",IF(L5>=52,"2 - Next",IF(L5>=44,"3 - Later","4 - Backlog"))) | N5: /products/balers
A6: 2 | B6: hydraulic baling press | C6: Balers | D6: Baler head | E6: Transactional | F6: India+Export | G6: 1300 | H6: 5400 | I6: 45 | J6: =100-I6 | K6: 100 | L6: =ROUND((G6/MAX($G$5:$G$271)*100*0.4)+(J6*0.35)+(K6*0.25),1) | M6: =IF(L6>=62,"1 - Do now",IF(L6>=52,"2 - Next",IF(L6>=44,"3 - Later","4 - Backlog"))) | N6: /products/balers
A7: 3 | B7: baling press machine | C7: Balers | D7: Baler head | E7: Transactional | F7: India+Export | G7: 1900 | H7: 6600 | I7: 47 | J7: =100-I7 | K7: 100 | L7: =ROUND((G7/MAX($G$5:$G$271)*100*0.4)+(J7*0.35)+(K7*0.25),1) | M7: =IF(L7>=62,"1 - Do now",IF(L7>=52,"2 - Next",IF(L7>=44,"3 - Later","4 - Backlog"))) | N7: /products/balers
A8: 4 | B8: scrap baler machine | C8: Balers | D8: Baler head | E8: Transactional | F8: India+Export | G8: 1100 | H8: 3600 | I8: 40 | J8: =100-I8 | K8: 100 | L8: =ROUND((G8/MAX($G$5:$G$271)*100*0.4)+(J8*0.35)+(K8*0.25),1) | M8: =IF(L8>=62,"1 - Do now",IF(L8>=52,"2 - Next",IF(L8>=44,"3 - Later","4 - Backlog"))) | N8: /products/balers
A9: 5 | B9: scrap bundling machine | C9: Balers | D9: Baler head | E9: Transactional | F9: India | G9: 720 | H9: 880 | I9: 33 | J9: =100-I9 | K9: 100 | L9: =ROUND((G9/MAX($G$5:$G$271)*100*0.4)+(J9*0.35)+(K9*0.25),1) | M9: =IF(L9>=62,"1 - Do now",IF(L9>=52,"2 - Next",IF(L9>=44,"3 - Later","4 - Backlog"))) | N9: /products/balers
A10: 6 | B10: hydraulic scrap baling press machine | C10: Balers | D10: Baler head | E10: Transactional | F10: India | G10: 720 | H10: 900 | I10: 34 | J10: =100-I10 | K10: 100 | L10: =ROUND((G10/MAX($G$5:$G$271)*100*0.4)+(J10*0.35)+(K10*0.25),1) | M10: =IF(L10>=62,"1 - Do now",IF(L10>=52,"2 - Next",IF(L10>=44,"3 - Later","4 - Backlog"))) | N10: /products/balers
A11: 7 | B11: metal baler machine | C11: Balers | D11: Baler head | E11: Transactional | F11: India+Export | G11: 590 | H11: 2900 | I11: 38 | J11: =100-I11 | K11: 100 | L11: =ROUND((G11/MAX($G$5:$G$271)*100*0.4)+(J11*0.35)+(K11*0.25),1) | M11: =IF(L11>=62,"1 - Do now",IF(L11>=52,"2 - Next",IF(L11>=44,"3 - Later","4 - Backlog"))) | N11: /products/balers
A12: 8 | B12: bundle press machine | C12: Balers | D12: Baler head | E12: Transactional | F12: India | G12: 480 | H12: 590 | I12: 30 | J12: =100-I12 | K12: 100 | L12: =ROUND((G12/MAX($G$5:$G$271)*100*0.4)+(J12*0.35)+(K12*0.25),1) | M12: =IF(L12>=62,"1 - Do now",IF(L12>=52,"2 - Next",IF(L12>=44,"3 - Later","4 - Backlog"))) | N12: /products/balers
A13: 9 | B13: scrap compactor machine | C13: Balers | D13: Baler head | E13: Transactional | F13: India+Export | G13: 390 | H13: 1600 | I13: 32 | J13: =100-I13 | K13: 100 | L13: =ROUND((G13/MAX($G$5:$G$271)*100*0.4)+(J13*0.35)+(K13*0.25),1) | M13: =IF(L13>=62,"1 - Do now",IF(L13>=52,"2 - Next",IF(L13>=44,"3 - Later","4 - Backlog"))) | N13: /products/balers
A14: 10 | B14: recycling baler machine | C14: Balers | D14: Baler head | E14: Transactional | F14: India+Export | G14: 320 | H14: 2400 | I14: 36 | J14: =100-I14 | K14: 100 | L14: =ROUND((G14/MAX($G$5:$G$271)*100*0.4)+(J14*0.35)+(K14*0.25),1) | M14: =IF(L14>=62,"1 - Do now",IF(L14>=52,"2 - Next",IF(L14>=44,"3 - Later","4 - Backlog"))) | N14: /products/balers
A15: 11 | B15: scrap baler machine price | C15: Balers | D15: Baler price | E15: Transactional | F15: India | G15: 880 | H15: 1300 | I15: 31 | J15: =100-I15 | K15: 100 | L15: =ROUND((G15/MAX($G$5:$G$271)*100*0.4)+(J15*0.35)+(K15*0.25),1) | M15: =IF(L15>=62,"1 - Do now",IF(L15>=52,"2 - Next",IF(L15>=44,"3 - Later","4 - Backlog"))) | N15: /products/balers
A16: 12 | B16: baling press machine price in india | C16: Balers | D16: Baler price | E16: Transactional | F16: India | G16: 720 | H16: 880 | I16: 29 | J16: =100-I16 | K16: 100 | L16: =ROUND((G16/MAX($G$5:$G$271)*100*0.4)+(J16*0.35)+(K16*0.25),1) | M16: =IF(L16>=62,"1 - Do now",IF(L16>=52,"2 - Next",IF(L16>=44,"3 - Later","4 - Backlog"))) | N16: /products/balers
... A271: 267 | B271: emission intensity targets iron and steel india | C271: Thought Leadership | D271: Policy & regulation | E271: Informational | F271: India | G271: 170 | H271: 390 | I271: 28 | J271: =100-I271 | K271: 40 | L271: =ROUND((G271/MAX($G$5:$G$271)*100*0.4)+(J271*0.35)+(K271*0.25),1) | M271: =IF(L271>=62,"1 - Do now",IF(L271>=52,"2 - Next",IF(L271>=44,"3 - Later","4 - Backlog"))) | N271: /blog/ccts-steel-scrap
B273: Source: manual keyword research, Aug 2026 — competitor page-one analysis, IndiaMART/TradeIndia category demand, search-suggest patterns. Directional estimates, not measured data. Rows 262-263 added 7 Aug 2026 from Plastic Waste Management (Amendment) Rules, 2026 research. Rows 264-265 added 8 Aug 2026 from NLM feed-and-fodder subsidy guidelines and the March 2026 ELV EPR amendment (removal of "other steel scrap materials"). Rows 266-267 added 11 Aug 2026 from the Carbon Credit Trading Scheme notification bringing iron and steel under intensity-based emission targets for compliance years FY2025-26 and FY2026-27 (ICAP).

Sheet Rank Tracker
A1: WEEKLY RANK TRACKER
A2: Enter Google position each Monday in the yellow dated columns. Leave BLANK if not ranking (do not type 0). Baseline Pos is a one-time entry.
A4: # | B4: Keyword | C4: Category | D4: Priority Band | E4: Current Pos | F4: Best Pos | G4: Baseline Pos | H4: Change | I4: Status | J4: 03-Aug-26 | K4: 10-Aug-26 | L4: 17-Aug-26 | M4: 24-Aug-26 | N4: 31-Aug-26 | O4: 07-Sep-26 | P4: 14-Sep-26 | Q4: 21-Sep-26 | R4: 28-Sep-26 | S4: 05-Oct-26 | T4: 12-Oct-26 | U4: 19-Oct-26 | V4: 26-Oct-26 | W4: 02-Nov-26 | X4: 09-Nov-26 | Y4: 16-Nov-26 | Z4: 23-Nov-26 | AA4: 30-Nov-26 | AB4: 07-Dec-26 | AC4: 14-Dec-26 | AD4: 21-Dec-26 | AE4: 28-Dec-26 | AF4: 04-Jan-27 | AG4: 11-Jan-27 | AH4: 18-Jan-27 | AI4: 25-Jan-27
A5: 1 | B5: ='Keyword Master'!B5 | C5: ='Keyword Master'!C5 | D5: ='Keyword Master'!M5 | E5: =IFERROR(LOOKUP(9.99E+307,J5:AI5),"") | F5: =IFERROR(SMALL(J5:AI5,1),"") | H5: =IF(OR(E5="",G5=""),"",G5-E5) | I5: =IF(E5="","Not tracked",IF(E5<=3,"Top 3",IF(E5<=10,"Page 1",IF(E5<=20,"Page 2 - near win","Page 3+"))))
A6: 2 | B6: ='Keyword Master'!B6 | C6: ='Keyword Master'!C6 | D6: ='Keyword Master'!M6 | E6: =IFERROR(LOOKUP(9.99E+307,J6:AI6),"") | F6: =IFERROR(SMALL(J6:AI6,1),"") | H6: =IF(OR(E6="",G6=""),"",G6-E6) | I6: =IF(E6="","Not tracked",IF(E6<=3,"Top 3",IF(E6<=10,"Page 1",IF(E6<=20,"Page 2 - near win","Page 3+"))))
A7: 3 | B7: ='Keyword Master'!B7 | C7: ='Keyword Master'!C7 | D7: ='Keyword Master'!M7 | E7: =IFERROR(LOOKUP(9.99E+307,J7:AI7),"") | F7: =IFERROR(SMALL(J7:AI7,1),"") | H7: =IF(OR(E7="",G7=""),"",G7-E7) | I7: =IF(E7="","Not tracked",IF(E7<=3,"Top 3",IF(E7<=10,"Page 1",IF(E7<=20,"Page 2 - near win","Page 3+"))))
A8: 4 | B8: ='Keyword Master'!B8 | C8: ='Keyword Master'!C8 | D8: ='Keyword Master'!M8 | E8: =IFERROR(LOOKUP(9.99E+307,J8:AI8),"") | F8: =IFERROR(SMALL(J8:AI8,1),"") | H8: =IF(OR(E8="",G8=""),"",G8-E8) | I8: =IF(E8="","Not tracked",IF(E8<=3,"Top 3",IF(E8<=10,"Page 1",IF(E8<=20,"Page 2 - near win","Page 3+"))))
A9: 5 | B9: ='Keyword Master'!B9 | C9: ='Keyword Master'!C9 | D9: ='Keyword Master'!M9 | E9: =IFERROR(LOOKUP(9.99E+307,J9:AI9),"") | F9: =IFERROR(SMALL(J9:AI9,1),"") | H9: =IF(OR(E9="",G9=""),"",G9-E9) | I9: =IF(E9="","Not tracked",IF(E9<=3,"Top 3",IF(E9<=10,"Page 1",IF(E9<=20,"Page 2 - near win","Page 3+"))))
A10: 6 | B10: ='Keyword Master'!B10 | C10: ='Keyword Master'!C10 | D10: ='Keyword Master'!M10 | E10: =IFERROR(LOOKUP(9.99E+307,J10:AI10),"") | F10: =IFERROR(SMALL(J10:AI10,1),"") | H10: =IF(OR(E10="",G10=""),"",G10-E10) | I10: =IF(E10="","Not tracked",IF(E10<=3,"Top 3",IF(E10<=10,"Page 1",IF(E10<=20,"Page 2 - near win","Page 3+"))))
A11: 7 | B11: ='Keyword Master'!B11 | C11: ='Keyword Master'!C11 | D11: ='Keyword Master'!M11 | E11: =IFERROR(LOOKUP(9.99E+307,J11:AI11),"") | F11: =IFERROR(SMALL(J11:AI11,1),"") | H11: =IF(OR(E11="",G11=""),"",G11-E11) | I11: =IF(E11="","Not tracked",IF(E11<=3,"Top 3",IF(E11<=10,"Page 1",IF(E11<=20,"Page 2 - near win","Page 3+"))))
A12: 8 | B12: ='Keyword Master'!B12 | C12: ='Keyword Master'!C12 | D12: ='Keyword Master'!M12 | E12: =IFERROR(LOOKUP(9.99E+307,J12:AI12),"") | F12: =IFERROR(SMALL(J12:AI12,1),"") | H12: =IF(OR(E12="",G12=""),"",G12-E12) | I12: =IF(E12="","Not tracked",IF(E12<=3,"Top 3",IF(E12<=10,"Page 1",IF(E12<=20,"Page 2 - near win","Page 3+"))))
A13: 9 | B13: ='Keyword Master'!B13 | C13: ='Keyword Master'!C13 | D13: ='Keyword Master'!M13 | E13: =IFERROR(LOOKUP(9.99E+307,J13:AI13),"") | F13: =IFERROR(SMALL(J13:AI13,1),"") | H13: =IF(OR(E13="",G13=""),"",G13-E13) | I13: =IF(E13="","Not tracked",IF(E13<=3,"Top 3",IF(E13<=10,"Page 1",IF(E13<=20,"Page 2 - near win","Page 3+"))))
A14: 10 | B14: ='Keyword Master'!B14 | C14: ='Keyword Master'!C14 | D14: ='Keyword Master'!M14 | E14: =IFERROR(LOOKUP(9.99E+307,J14:AI14),"") | F14: =IFERROR(SMALL(J14:AI14,1),"") | H14: =IF(OR(E14="",G14=""),"",G14-E14) | I14: =IF(E14="","Not tracked",IF(E14<=3,"Top 3",IF(E14<=10,"Page 1",IF(E14<=20,"Page 2 - near win","Page 3+"))))
A15: 11 | B15: ='Keyword Master'!B15 | C15: ='Keyword Master'!C15 | D15: ='Keyword Master'!M15 | E15: =IFERROR(LOOKUP(9.99E+307,J15:AI15),"") | F15: =IFERROR(SMALL(J15:AI15,1),"") | H15: =IF(OR(E15="",G15=""),"",G15-E15) | I15: =IF(E15="","Not tracked",IF(E15<=3,"Top 3",IF(E15<=10,"Page 1",IF(E15<=20,"Page 2 - near win","Page 3+"))))
A16: 12 | B16: ='Keyword Master'!B16 | C16: ='Keyword Master'!C16 | D16: ='Keyword Master'!M16 | E16: =IFERROR(LOOKUP(9.99E+307,J16:AI16),"") | F16: =IFERROR(SMALL(J16:AI16,1),"") | H16: =IF(OR(E16="",G16=""),"",G16-E16) | I16: =IF(E16="","Not tracked",IF(E16<=3,"Top 3",IF(E16<=10,"Page 1",IF(E16<=20,"Page 2 - near win","Page 3+"))))
... A265: 261 | B265: ='Keyword Master'!B265 | C265: ='Keyword Master'!C265 | D265: ='Keyword Master'!M265 | E265: =IFERROR(LOOKUP(9.99E+307,J265:AI265),"") | F265: =IFERROR(SMALL(J265:AI265,1),"") | H265: =IF(OR(E265="",G265=""),"",G265-E265) | I265: =IF(E265="","Not tracked",IF(E265<=3,"Top 3",IF(E265<=10,"Page 1",IF(E265<=20,"Page 2 - near win","Page 3+"))))
B267: EXAMPLE (delete before use): | C267: scrap baling press machine | J267: 38 | K267: 34 | L267: 29 | M267: 24 | N267: 19 | O267: 15 | P267: 11

Sheet Traffic & Conversions
A1: TRAFFIC & CONVERSIONS BY LANDING PAGE
A2: Paste weekly figures from Google Search Console and your enquiry inbox / CRM. Yellow = your input.
A4: Week Starting | B4: Landing Page / URL | C4: Primary Keyword | D4: Impressions | E4: Clicks | F4: CTR % | G4: Avg Position | H4: Enquiries | I4: Enquiry Rate % | J4: Notes
A5: 2026-08-03 | B5: /blog/types-of-scrap-baling-machines | C5: types of scrap baling machines | D5: 1240 | E5: 63 | F5: =IFERROR(E5/D5,"") | G5: 18.4 | H5: 4 | I5: =IFERROR(H5/E5,"") | J5: EXAMPLE ROW — delete before use
F6: =IFERROR(E6/D6,"") | I6: =IFERROR(H6/E6,"")
F7: =IFERROR(E7/D7,"") | I7: =IFERROR(H7/E7,"")
F8: =IFERROR(E8/D8,"") | I8: =IFERROR(H8/E8,"")
F9: =IFERROR(E9/D9,"") | I9: =IFERROR(H9/E9,"")
F10: =IFERROR(E10/D10,"") | I10: =IFERROR(H10/E10,"")
F11: =IFERROR(E11/D11,"") | I11: =IFERROR(H11/E11,"")
F12: =IFERROR(E12/D12,"") | I12: =IFERROR(H12/E12,"")
F13: =IFERROR(E13/D13,"") | I13: =IFERROR(H13/E13,"")
F14: =IFERROR(E14/D14,"") | I14: =IFERROR(H14/E14,"")
F15: =IFERROR(E15/D15,"") | I15: =IFERROR(H15/E15,"")
F16: =IFERROR(E16/D16,"") | I16: =IFERROR(H16/E16,"")
F17: =IFERROR(E17/D17,"") | I17: =IFERROR(H17/E17,"")
... F155: =IFERROR(E155/D155,"") | I155: =IFERROR(H155/E155,"")
C157: TOTALS | D157: =SUM(D6:D155) | E157: =SUM(E6:E155) | F157: =IFERROR(E157/D157,0) | H157: =SUM(H6:H155) | I157: =IFERROR(H157/E157,0)

Sheet Competitor Audit
A1: COMPETITOR AUDIT — AUGUST 2026
A2: Manual audit of live sites. Blog post counts approximate (from visible pagination). Re-check monthly.
A4: Competitor | B4: Domain | C4: Platform | D4: Owns Domain? | E4: Has Blog? | F4: Est. Blog Posts | G4: Product URL Structure | H4: Schema Markup | I4: OG Image OK? | J4: Strengths | K4: Weaknesses | L4: Threat
A5: Jindal Hydro Projects (IndiaMART site) | B5: jindalhydro.com → jindalhydraulics.com | C5: IndiaMART microsite | D5: No | E5: No | F5: 0 | G5: Anchor fragments (#product) — products cannot rank individually | H5: Minimal | I5: No (120x120) | J5: Established listing, 93% response rate, GST/IEC shown | K5: Not an owned site; no blog; no schema; obsolete meta-keywords; thin templated copy; products share one URL | L5: SELF
A6: Jindal Hydro Projects (TradeIndia site) | B6: jindalhydroprojects.com | C6: TradeIndia microsite | D6: No | E6: No | F6: 0 | G6: Individual .html URLs per product (better than IndiaMART) | H6: Minimal | I6: Templated | J6: Individual product URLs; prices listed; GTM + Search Console verified; export markets named | K6: Not an owned site; no blog; templated boilerplate copy; platform-controlled; duplicate of IndiaMART content | L6: SELF
A7: Jain Hydraulics Recycling | B7: jainhydraulics.com | C7: Own domain (Astro static) | D7: Yes | E7: Yes | F7: 8 | G7: Clean hierarchy /products/balers/triple-action | H7: Partial | I7: Yes | J7: Own domain; clean URL taxonomy; real blog; 2 locations (Delhi + Pune); WhatsApp; active YouTube/Instagram; strong meta setup | K7: Only ~8 blog posts and they are short; no RVSF/ELV positioning; no agriculture range; no visible schema markup | L7: HIGH
A8: Advance Hydrautech | B8: advancehydrautech.com | C8: Own domain (WordPress) | D8: Yes | E8: Yes | F8: 20 | G8: /blog/blog_details/slug | H8: Partial | I8: Unknown | J8: Own domain; blog established since 2014; claims 'India's largest'; long domain history | K8: Dated site architecture; blog URL structure poor; thin posts; weak technical SEO | L8: MEDIUM
A9: Shreeji Machinery | B9: shreejimachineryindia.com | C9: Own domain | D9: Yes | E9: No | F9: 0 | G9: /product-name.html | H9: Minimal | I9: Unknown | J9: Own domain; wide product range; Ahmedabad hub; price transparency on IndiaMART | K9: No blog; thin product copy; little differentiation; heavy IndiaMART dependence | L9: MEDIUM
A10: JMD Industries | B10: jmdbaler.com | C10: Own domain | D10: Yes | E10: Yes | F10: 10 | G10: /blog/slug | H10: Unknown | I10: Unknown | J10: Own domain with blog; baler-focused brand name matches head keyword | K10: Small content footprint; narrow product range | L10: MEDIUM
A11: Kelvin Water Technologies | B11: kelvinindia.in | C11: Own domain (WordPress) | D11: Yes | E11: Yes | F11: 30 | G11: /blog/slug | H11: Partial | I11: Yes | J11: Strong blog cadence; broad environmental-equipment authority; ranks on informational terms | K11: Balers are a side line, not core; generalist positioning dilutes topical authority | L11: MEDIUM
A12: Mask Hydraulics | B12: maskhydraulics.com | C12: Own domain | D12: Yes | E12: No | F12: 0 | G12: /product.html | H12: Minimal | I12: Unknown | J12: Own domain; Ahmedabad manufacturing hub; export positioning | K12: No blog; static thin content; weak on-page SEO | L12: LOW
A13: IndiaMART (category pages) | B13: dir.indiamart.com | C13: Marketplace | D13: Yes | E13: No | F13: 0 | G13: /impcat/keyword.html | H13: Yes | I13: Yes | J13: Dominates page one for nearly every commercial head term; enormous domain authority; price aggregation | K13: Not a manufacturer — a directory. Cannot be beaten on head terms; must be outflanked on informational and long-tail | L13: VERY HIGH
A14: TradeIndia (category pages) | B14: tradeindia.com | C14: Marketplace | D14: Yes | E14: No | F14: 0 | G14: /manufacturers/keyword.html | H14: Yes | I14: Yes | J14: Same as IndiaMART — directory dominance on transactional head terms | K14: Directory, not manufacturer; no depth on how-to or specification content | L14: VERY HIGH
A15: PRAB (US) | B15: prab.com | C15: Own domain (WordPress + Yoast) | D15: Yes | E15: Yes | F15: 100 | G15: /metal-scrap-processing-equipment/category/ | H15: Yes (Article) | I15: Yes | J15: Benchmark for the category: benefit-led meta descriptions with hard numbers ('capture up to 99% of coolant', 'ROI within one year'), deep resource library, FAQ hub, video embeds, published/modified timestamps | K15: US-focused; not a competitor for Indian buyers — but the model to copy for content depth | L15: REFERENCE
A16: Sinobaler (China) | B16: sinobaler.com | C16: Own domain | D16: Yes | E16: Yes | F16: 50 | G16: /category/product | H16: Partial | I16: Yes | J16: Strong export SEO; ranks internationally on generic baler terms; clear capacity specs upfront | K16: Chinese-origin perception in some export markets — an opening for Indian manufacturers on quality/service | L16: REFERENCE
A17: WEIMA (Germany) | B17: weima.com | C17: Own domain | D17: Yes | E17: Yes | F17: 80 | G17: /en/category/ | H17: Yes | I17: Yes | J17: Premium positioning; excellent technical content depth; multi-language | K17: Premium price point; not price-competitive in India/Africa/South Asia | L17: REFERENCE
A19: KEY TAKEAWAY: IndiaMART and TradeIndia own the transactional head terms and cannot be beaten there. Jain Hydraulics is the only Indian manufacturer with a real owned site plus blog — and it has roughly 8 short posts. That is the opening: a proper JHP site publishing 2 researched posts a day would out-cover every Indian competitor within one month, on informational, comparison, spares and RVSF terms none of them target.

Sheet Content Gaps
A1: CONTENT GAPS — WHAT NOBODY OWNS YET
A2: Ranked by opportunity. These are the topic areas where JHP can rank fastest because no competitor has covered them.
A4: Topic Area | B4: Why It's A Gap | C4: Who Owns It Now | D4: Difficulty | E4: Opportunity Score | F4: Target Cluster
A5: RVSF / ELV machinery guidance | B5: Almost no Indian machinery manufacturer publishes serious RVSF setup content. Policy demand is rising fast and searches are commercial-intent. | C5: Consultants and news sites, not manufacturers | D5: Low | E5: 95 | F5: ELV / RVSF
A6: Machine specification deep-dives | B6: Competitors list specs in tables but nobody explains what cylinder force, cycle time or BHN grade actually mean for buying decisions. | C6: Nobody | D6: Low | E6: 90 | F6: Informational
A7: Comparison content (X vs Y) | B7: Buyers search these constantly. Zero Indian manufacturers publish honest comparisons. | C7: Nobody | D7: Very Low | E7: 88 | F7: Comparison
A8: Total cost of ownership / ROI maths | B8: PRAB does this well in the US. No Indian manufacturer publishes payback calculations. | C8: PRAB (US only) | D8: Low | E8: 87 | F8: Briquetting/Balers
A9: Spares, service and AMC content | B9: Very high commercial intent, almost no competition. Existing owners search these terms. | C9: Nobody | D9: Very Low | E9: 85 | F9: Service & Spares
A10: Agriculture waste machinery | B10: Fodder block and straw baling content is thin, and stubble-burning policy drives large seasonal search volume. | C10: Government/NGO sites | D10: Low | E10: 82 | F10: Agriculture
A11: Maintenance and troubleshooting | B11: Retains existing customers and captures owners of competitor machines. | C11: Nobody | D11: Very Low | E11: 80 | F11: Informational
A12: Local/city landing pages | B12: Nobody has built city-level pages for scrap machinery in India. | C12: IndiaMART only | D12: Very Low | E12: 78 | F12: Local SEO
A13: Case studies with named outcomes | B13: No Indian manufacturer publishes installation case studies with throughput/payback numbers. | C13: Nobody | D13: Low | E13: 76 | F13: Trust
A14: Export buyer guidance | B14: Overseas buyers searching for Indian suppliers find directories, not manufacturer guidance on documentation, terms and inspection. | C14: Nobody | D14: Low | E14: 75 | F14: Export
A15: Video + schema-rich product pages | B15: Jain Hydraulics has video; nobody has combined video with Product/FAQ schema for rich results. | C15: Nobody | D15: Medium | E15: 72 | F15: Technical
A16: Scrap grades and pricing education | B16: High search volume (GST on scrap, scrap grades). Draws in the whole buyer universe. | C16: Accounting/news sites | D16: Medium | E16: 70 | F16: Informational

Sheet Blog Pipeline
A1: BLOG PIPELINE — 2/DAY MON-SAT + SUNDAY DEEP DIVE
A2: Auto-ordered by Priority Score. Titles are working titles — the daily run refines them after that day's keyword research.
A4: Day | B4: Date | C4: Weekday | D4: Slot | E4: Type | F4: Working Title | G4: Primary Keyword | H4: Category | I4: Intent | J4: Target Words | K4: Target Page | L4: Written?
A5: 1 | B5: 03-Aug-2026 | C5: Mon | D5: 1 | E5: Standard | F5: RVSF Machinery Checklist: Every Machine You Need to Set Up a Vehicle Scrapping Facility in India | G5: rvsf machinery | H5: ELV / RVSF | I5: Transactional | J5: 1768 | K5: /blog/rvsf-machinery-checklist-india | L5: YES
A6: 1 | B6: 03-Aug-2026 | C6: Mon | D6: 2 | E6: Standard | F6: Metal Briquetting Machines: How Chip Recycling Pays for Itself | G6: metal briquetting machine | H6: Briquetting | I6: Transactional | J6: 1481 | K6: /blog/metal-briquetting-machine-roi | L6: YES
A7: 1 | B7: 03-Aug-2026 | C7: Mon | D7: 3 | E7: Standard | F7: Types of Scrap Baling Machines: A Buyer's Guide to Choosing the Right Press | G7: types of scrap baling machines | H7: Informational | I7: Transactional | J7: 1886 | K7: /blog/types-of-scrap-baling-machines | L7: YES
A8: 2 | B8: 04-Aug-2026 | C8: Tue | D8: 1 | E8: Standard | F8: Baling press machine: Specifications, Sizing and What to Check Before You Buy | G8: baling press machine | H8: Balers | I8: Transactional | J8: 1500 | K8: /products/balers
A9: 2 | B9: 04-Aug-2026 | C9: Tue | D9: 2 | E9: Standard | F9: Scrap Baling Press Machine: How to Read the Spec Sheet and Size the Press | G9: scrap baling press machine | H9: Balers | I9: Transactional | J9: 1878 | K9: /products/balers | L9: YES
A10: 3 | B10: 05-Aug-2026 | C10: Wed | D10: 1 | E10: Standard | F10: Vehicle Scrapping Policy India 2026: What Buyers Need to Know | G10: vehicle scrapping policy india 2026 | H10: ELV / RVSF | I10: Informational | J10: 1904 | K10: /blog/vehicle-scrappage-policy | L10: YES
A11: 3 | B11: 05-Aug-2026 | C11: Wed | D11: 2 | E11: Standard | F11: Plastic Waste Management Rules in India: What the 2026 Amendment Changes for Processors | G11: plastic waste management rules india | H11: Thought Leadership | I11: Informational | J11: 1829 | K11: /blog/plastic-waste-rules | L11: YES
A12: 4 | B12: 06-Aug-2026 | C12: Thu | D12: 1 | E12: Standard | F12: Hydraulic Baling Press: How the Hydraulics Actually Work, and What Goes Wrong | G12: hydraulic baling press | H12: Balers | I12: Transactional | J12: 2024 | K12: /products/balers | L12: YES
A13: 4 | B13: 06-Aug-2026 | C13: Thu | D13: 2 | E13: Standard | F13: Scrap baler machine: Specifications, Sizing and What to Check Before You Buy | G13: scrap baler machine | H13: Balers | I13: Transactional | J13: 1500 | K13: /products/balers
A14: 5 | B14: 07-Aug-2026 | C14: Fri | D14: 1 | E14: Standard | F14: Scrap Baler Machine Price: What You Are Actually Paying For | G14: scrap baler machine price | H14: Balers | I14: Transactional | J14: 1847 | K14: /products/balers | L14: YES
A15: 5 | B15: 07-Aug-2026 | C15: Fri | D15: 2 | E15: Standard | F15: GST on Scrap Metal in India: The Rate, Reverse Charge and the 2% TDS Rule | G15: gst rate on scrap metal india | H15: Informational | I15: Informational | J15: 1837 | K15: /blog/scrap-gst | L15: YES
A16: 6 | B16: 08-Aug-2026 | C16: Sat | D16: 1 | E16: Standard | F16: Baling Press Machine Price in India: How to Build the Budget Before You Ask for a Quote | G16: baling press machine price in india | H16: Balers | I16: Transactional | J16: 2032 | K16: /blog/baling-press-machine-price-in-india | L16: YES
A17: 6 | B17: 08-Aug-2026 | C17: Sat | D17: 2 | E17: Standard | F17: Fodder Block Making Machine: Specifications, Output and the NLM Subsidy Route | G17: fodder block making machine | H17: Agriculture | I17: Transactional | J17: 1884 | K17: /blog/fodder-block-making-machine | L17: YES
A18: 7 | B18: 09-Aug-2026 | C18: Sun | D18: 1 | E18: DEEP DIVE | F18: Straw baler machine price india: Specifications, Sizing and What to Check Before You Buy | G18: straw baler machine price india | H18: Agriculture | I18: Transactional | J18: 2500 | K18: /products/straw-baler
A19: 8 | B19: 10-Aug-2026 | C19: Mon | D19: 1 | E19: Standard | F19: Scrap bundling machine: Specifications, Sizing and What to Check Before You Buy | G19: scrap bundling machine | H19: Balers | I19: Transactional | J19: 1500 | K19: /products/balers | L19: YES
A20: 8 | B20: 10-Aug-2026 | C20: Mon | D20: 2 | E20: Standard | F20: Hydraulic scrap baling press machine: Specifications, Sizing and What to Check Before You Buy | G20: hydraulic scrap baling press machine | H20: Balers | I20: Transactional | J20: 1500 | K20: /products/balers | L20: YES
A21: 9 | B21: 11-Aug-2026 | C21: Tue | D21: 1 | E21: Standard | F21: How to start a vehicle scrapping business in india? | G21: how to start a vehicle scrapping business in india | H21: ELV / RVSF | I21: Commercial | J21: 1500 | K21: /blog/start-rvsf-india | L21: YES
A22: 9 | B22: 11-Aug-2026 | C22: Tue | D22: 2 | E22: Standard | F22: Alligator shear machine: Specifications, Sizing and What to Check Before You Buy | G22: alligator shear machine | H22: Shears & Nibblers | I22: Transactional | J22: 1500 | K22: /products/alligator-shear | L22: YES
A23: 10 | B23: 12-Aug-2026 | C23: Wed | D23: 1 | E23: Standard | F23: Baler Machine Manufacturer in Alwar: How to Evaluate One Before You Buy | G23: baler machine manufacturer in alwar | H23: Local SEO | I23: Transactional | J23: 1991 | K23: /locations | L23: YES
A24: 10 | B24: 12-Aug-2026 | C24: Wed | D24: 2 | E24: Standard | F24: Second Hand Baling Press Machine for Sale: What to Inspect, and When to Walk Away | G24: second hand baling press machine for sale | H24: Balers | I24: Transactional | J24: 2223 | K24: /blog/used-vs-new-baler | L24: YES
A25: 11 | B25: 13-Aug-2026 | C25: Thu | D25: 1 | E25: Standard | F25: Baling Press Spare Parts: What Wears Out, When, and What to Keep on the Shelf | G25: baling press spare parts | H25: Service & Spares | I25: Transactional | J25: 2459 | K25: /spares | L25: YES
A26: 11 | B26: 13-Aug-2026 | C26: Thu | D26: 2 | E26: Standard | F26: Scrap Baling Press Machine in Alwar: Sizing One for the Alwar–Bhiwadi Scrap Mix | G26: scrap baling press machine in alwar | H26: Local SEO | I26: Transactional | J26: 2539 | K26: /locations | L26: YES
A27: 12 | B27: 14-Aug-2026 | C27: Fri | D27: 1 | E27: Standard | F27: Pet bottle baling machine: Specifications, Sizing and What to Check Before You Buy | G27: pet bottle baling machine | H27: Balers | I27: Transactional | J27: 1500 | K27: /products/automatic-horizontal-baler
A28: 12 | B28: 14-Aug-2026 | C28: Fri | D28: 2 | E28: Standard | F28: Scrap baling press machine in mandi gobindgarh: Specifications, Sizing and What to Check Before You Buy | G28: scrap baling press machine in mandi gobindgarh | H28: Local SEO | I28: Transactional | J28: 1500 | K28: /locations
A29: 13 | B29: 15-Aug-2026 | C29: Sat | D29: 1 | E29: Standard | F29: Silage baler machine india: Specifications, Sizing and What to Check Before You Buy | G29: silage baler machine india | H29: Agriculture | I29: Transactional | J29: 1500 | K29: /products/straw-baler
A30: 13 | B30: 15-Aug-2026 | C30: Sat | D30: 2 | E30: Standard | F30: Scrap baling press machine in bhiwadi: Specifications, Sizing and What to Check Before You Buy | G30: scrap baling press machine in bhiwadi | H30: Local SEO | I30: Transactional | J30: 1500 | K30: /locations
A31: 14 | B31: 16-Aug-2026 | C31: Sun | D31: 1 | E31: DEEP DIVE | F31: Scrap baling press machine in jaipur: Specifications, Sizing and What to Check Before You Buy | G31: scrap baling press machine in jaipur | H31: Local SEO | I31: Transactional | J31: 2500 | K31: /locations
A32: 15 | B32: 17-Aug-2026 | C32: Mon | D32: 1 | E32: Standard | F32: Baler machine manufacturer in mandi gobindgarh: Specifications, Sizing and What to Check Before You Buy | G32: baler machine manufacturer in mandi gobindgarh | H32: Local SEO | I32: Transactional | J32: 1500 | K32: /locations
A33: 15 | B33: 17-Aug-2026 | C33: Mon | D33: 2 | E33: Standard | F33: Metal shredder machine: Specifications, Sizing and What to Check Before You Buy | G33: metal shredder machine | H33: Shredders & Crackers | I33: Transactional | J33: 1500 | K33: /products/shredders
A34: 16 | B34: 18-Aug-2026 | C34: Tue | D34: 1 | E34: Standard | F34: Baler machine manufacturer in jaipur: Specifications, Sizing and What to Check Before You Buy | G34: baler machine manufacturer in jaipur | H34: Local SEO | I34: Transactional | J34: 1500 | K34: /locations
A35: 16 | B35: 18-Aug-2026 | C35: Tue | D35: 2 | E35: Standard | F35: Baling press amc service india: Specifications, Sizing and What to Check Before You Buy | G35: baling press amc service india | H35: Service & Spares | I35: Transactional | J35: 1500 | K35: /service
A36: 17 | B36: 19-Aug-2026 | C36: Wed | D36: 1 | E36: Standard | F36: Triple action baling press: Specifications, Sizing and What to Check Before You Buy | G36: triple action baling press | H36: Balers | I36: Transactional | J36: 1500 | K36: /products/triple-action-baler
A37: 17 | B37: 19-Aug-2026 | C37: Wed | D37: 2 | E37: Standard | F37: Hydraulic cylinder for baling press: Specifications, Sizing and What to Check Before You Buy | G37: hydraulic cylinder for baling press | H37: Service & Spares | I37: Transactional | J37: 1500 | K37: /spares
A38: 18 | B38: 20-Aug-2026 | C38: Thu | D38: 1 | E38: Standard | F38: Plastic baling machine: Specifications, Sizing and What to Check Before You Buy | G38: plastic baling machine | H38: Balers | I38: Transactional | J38: 1500 | K38: /products/automatic-horizontal-baler
... A69: 34 | B69: 05-Sep-2026 | C69: Sat | D69: 2 | E69: Standard | F69: Baling press manufacturer in india: Specifications, Sizing and What to Check Before You Buy | G69: baling press manufacturer in india | H69: Balers | I69: Transactional | J69: 1500 | K69: /about

Sheet Content Map
A1: CONTENT MAP — BLOG TO KEYWORD
A2: One primary keyword per blog. Update Status and Live URL as posts go out.
A4: Blog Title | B4: Primary Keyword | C4: Secondary Keywords | D4: Category | E4: Type | F4: Words | G4: Publish Date | H4: Live URL | I4: Status | J4: Internal Links To | K4: CTA Used | L4: Sources Cited
A5: RVSF Machinery Checklist: Every Machine You Need to Set Up a Vehicle Scrapping Facility in India | B5: rvsf machinery | D5: ELV / RVSF | E5: Standard | F5: 1768 | G5: 2026-08-03 | I5: Draft | K5: Mid-article + closing CTA | L5: 5
A6: Metal Briquetting Machines: How Chip Recycling Pays for Itself | B6: metal briquetting machine | D6: Briquetting | E6: Standard | F6: 1481 | G6: 2026-08-03 | I6: Draft | K6: Mid-article + closing CTA | L6: 5
A7: Types of Scrap Baling Machines: A Buyer's Guide to Choosing the Right Press | B7: types of scrap baling machines | D7: Informational | E7: Standard | F7: 1886 | G7: 2026-08-03 | I7: Draft | K7: Mid-article + closing CTA | L7: 4
A8: Baling press machine: Specifications, Sizing and What to Check Before You Buy | B8: baling press machine | D8: Balers | E8: Standard | F8: 1500 | G8: 2026-08-04
A9: Scrap Baling Press Machine: How to Read the Spec Sheet and Size the Press | B9: scrap baling press machine | C9: baling press specifications; how to size a baling press; bale size vs chamber size; baling press cycle time; scrap baler capacity calculation | D9: Balers | E9: Standard | F9: 1878 | G9: 2026-08-04 | I9: Draft | J9: /blog/types-of-scrap-baling-machines; /blog/scrap-baler-machine-price; /contact | K9: Mid-article + closing CTA | L9: 4
A10: Vehicle Scrapping Policy India 2026: What Buyers Need to Know | B10: vehicle scrapping policy india 2026 | D10: ELV / RVSF | E10: Standard | F10: 1904 | G10: 2026-08-05 | I10: Draft | J10: /contact | K10: Mid-article + closing CTA | L10: 5
A11: Plastic Waste Management Rules in India: What the 2026 Amendment Changes for Processors | B11: plastic waste management rules india | C11: plastic waste management amendment rules 2026; EPR recycled content targets India; plastic waste processor registration; IS 14534 recycled plastic; baling machine for plastic recycling | D11: Thought Leadership | E11: Standard | F11: 1829 | G11: 2026-08-05 | I11: Draft | J11: /contact | K11: Mid-article + closing CTA | L11: 4
A12: Hydraulic Baling Press: How the Hydraulics Actually Work, and What Goes Wrong | B12: hydraulic baling press | C12: baling press hydraulic system; baling press cylinder force calculation; hydraulic press overheating; hydraulic oil contamination baler; baling press troubleshooting | D12: Balers | E12: Standard | F12: 2024 | G12: 2026-08-06 | I12: Draft | J12: /blog/scrap-baling-press-machine; /blog/scrap-baler-machine-price; /contact | K12: Mid-article + closing CTA | L12: 4
A13: Scrap baler machine: Specifications, Sizing and What to Check Before You Buy | B13: scrap baler machine | D13: Balers | E13: Standard | F13: 1500 | G13: 2026-08-06
A14: Scrap Baler Machine Price: What You Are Actually Paying For | B14: scrap baler machine price | C14: baling press cost india; hydraulic baler machine cost; baler machine quotation checklist; scrap baling machine running cost; how to compare baler quotations | D14: Balers | E14: Standard | F14: 1847 | G14: 2026-08-07 | I14: Draft | J14: /products/balers; /blog/types-of-scrap-baling-machines; /blog/rvsf-machinery-checklist-india; /contact | K14: Mid-article + closing CTA | L14: 4
A15: GST on Scrap Metal in India: The Rate, Reverse Charge and the 2% TDS Rule | B15: gst rate on scrap metal india | C15: rcm on metal scrap; gst tds on scrap 2 percent; hsn code for scrap metal; gst on baling machine; input tax credit on recycling machinery | D15: Informational | E15: Standard | F15: 1837 | G15: 2026-08-07 | I15: Draft | J15: /contact; /catalogue | K15: Mid-article + closing CTA | L15: 5
A16: Baling Press Machine Price in India: How to Build the Budget Before You Ask for a Quote | B16: baling press machine price in india | C16: baling press cost india; hydraulic baling press budget; baling press installed cost; baling press capacity sizing; baling press running cost per tonne | D16: Balers | E16: Standard | F16: 2032 | G16: 2026-08-08 | I16: Draft | J16: /blog/scrap-baler-machine-price; https://www.scrapmonster.com/india-scrap-prices; /contact | K16: Mid-article + closing CTA | L16: 4
A17: Fodder Block Making Machine: Specifications, Output and the NLM Subsidy Route | B17: fodder block making machine | C17: fodder block machine specifications; TMR block making machine india; NLM subsidy fodder block unit; cattle feed block machine output; fodder block machine capacity | D17: Agriculture | E17: Standard | F17: 1884 | G17: 2026-08-08 | I17: Draft | J17: /contact | K17: Mid-article + closing CTA | L17: 4
A18: Straw baler machine price india: Specifications, Sizing and What to Check Before You Buy | B18: straw baler machine price india | D18: Agriculture | E18: DEEP DIVE | F18: 2500 | G18: 2026-08-09
A19: Scrap Bundling Machine: What the Term Means, and Which Press Makes Your Bundle | B19: scrap bundling machine | C19: scrap bundling press; bundling machine vs baling machine; car baler bundles; bale weight for furnace charging; scrap bundling machine specifications | D19: Balers | E19: Standard | F19: 1829 | G19: 2026-08-10 | I19: Draft | J19: /blog/types-of-scrap-baling-machines; /blog/scrap-baling-press-machine; /products/balers; /contact | K19: Mid-article + closing CTA | L19: 4
A20: Hydraulic Scrap Baling Press Machine: The Site, Power and Commissioning Checklist | B20: hydraulic scrap baling press machine | C20: baling press foundation requirement; baling press power supply sanctioned load; baling press installation checklist; baling press commissioning acceptance test; hydraulic oil cleanliness baling press | D20: Balers | E20: Standard | F20: 1926 | G20: 2026-08-10 | I20: Draft | J20: /blog/hydraulic-baling-press; /blog/baling-press-machine-price-in-india; /products/balers; /contact | K20: Mid-article + closing CTA | L20: 4
A21: How to Start a Vehicle Scrapping Business in India: Approvals, Site and Machinery | B21: how to start a vehicle scrapping business in india | C21: rvsf registration process; vehicle scrapping business setup cost; rvsf licence requirements; certificate of deposit vehicle scrapping; elv recycling plant india | D21: ELV / RVSF | E21: Standard | F21: 1972 | G21: 2026-08-11 | I21: Draft | J21: /blog/rvsf-machinery-checklist-india; /blog/vehicle-scrapping-policy; /products/car-baler; /contact | K21: Mid-article + closing CTA | L21: 5
A22: Alligator Shear Machine: How to Size One, and When You Need Something Else | B22: alligator shear machine | C22: alligator shear specifications; alligator shear cutting capacity; alligator shear vs nibbler; scrap cutting machine india; hydraulic alligator shear sizing | D22: Shears & Nibblers | E22: Standard | F22: 1990 | G22: 2026-08-11 | I22: Draft | J22: /products/alligator-shear; /products/nibblers; /blog/start-rvsf-india; /contact | K22: Mid-article + closing CTA | L22: 4
A23: Baler Machine Manufacturer in Alwar: How to Evaluate One Before You Buy | B23: baler machine manufacturer in alwar | C23: baling press manufacturer alwar rajasthan; matsya industrial area alwar machinery; how to choose a baler manufacturer; baler factory visit checklist; scrap baling machine supplier rajasthan | D23: Local SEO | E23: Standard | F23: 1991 | G23: 2026-08-12 | I23: Draft | J23: /products/balers; /catalogue; /contact | K23: Mid-article + closing CTA | L23: 4
A24: Second Hand Baling Press Machine for Sale: What to Inspect, and When to Walk Away | B24: second hand baling press machine for sale | C24: used baling press machine india; refurbished baler machine buying guide; second hand scrap baler inspection checklist; used hydraulic press machine import india; old baling machine for sale risks | D24: Balers | E24: Standard | F24: 2223 | G24: 2026-08-12 | I24: Draft | J24: /products/balers; /blog/baling-press-machine-price-in-india; /blog/hydraulic-baling-press; /contact | K24: Mid-article + closing CTA | L24: 4
A25: Baling Press Spare Parts: What Wears Out, When, and What to Keep on the Shelf | B25: baling press spare parts | C25: baler wear plate replacement; baling press seal kit; baler shear blade replacement; hydraulic power pack spares baler; baling press preventive maintenance | D25: Service & Spares | E25: Standard | F25: 2459 | G25: 2026-08-13 | I25: Draft | J25: /spares; /products/balers; /contact | K25: Mid-article + closing CTA | L25: 4
A26: Scrap Baling Press Machine in Alwar: Sizing One for the Alwar–Bhiwadi Scrap Mix | B26: scrap baling press machine in alwar | C26: baling press for rolling mill scrap rajasthan; bale size for induction furnace charging; rvsf rajasthan machinery requirements; baling press power supply requirement; alwar bhiwadi scrap belt | D26: Local SEO | E26: Standard | F26: 2539 | G26: 2026-08-13 | I26: Draft | J26: /blog/baler-machine-manufacturer-in-alwar; /products/balers; /products/briquetting; /contact | K26: Mid-article + closing CTA | L26: 4
A27: Pet bottle baling machine: Specifications, Sizing and What to Check Before You Buy | B27: pet bottle baling machine | D27: Balers | E27: Standard | F27: 1500 | G27: 2026-08-14
A28: Scrap baling press machine in mandi gobindgarh: Specifications, Sizing and What to Check Before You Buy | B28: scrap baling press machine in mandi gobindgarh | D28: Local SEO | E28: Standard | F28: 1500 | G28: 2026-08-14
A29: Silage baler machine india: Specifications, Sizing and What to Check Before You Buy | B29: silage baler machine india | D29: Agriculture | E29: Standard | F29: 1500 | G29: 2026-08-15
A30: Scrap baling press machine in bhiwadi: Specifications, Sizing and What to Check Before You Buy | B30: scrap baling press machine in bhiwadi | D30: Local SEO | E30: Standard | F30: 1500 | G30: 2026-08-15
A31: Scrap baling press machine in jaipur: Specifications, Sizing and What to Check Before You Buy | B31: scrap baling press machine in jaipur | D31: Local SEO | E31: DEEP DIVE | F31: 2500 | G31: 2026-08-16
A32: Baler machine manufacturer in mandi gobindgarh: Specifications, Sizing and What to Check Before You Buy | B32: baler machine manufacturer in mandi gobindgarh | D32: Local SEO | E32: Standard | F32: 1500 | G32: 2026-08-17
A33: Metal shredder machine: Specifications, Sizing and What to Check Before You Buy | B33: metal shredder machine | D33: Shredders & Crackers | E33: Standard | F33: 1500 | G33: 2026-08-17
A34: Baler machine manufacturer in jaipur: Specifications, Sizing and What to Check Before You Buy | B34: baler machine manufacturer in jaipur | D34: Local SEO | E34: Standard | F34: 1500 | G34: 2026-08-18
A35: Baling press amc service india: Specifications, Sizing and What to Check Before You Buy | B35: baling press amc service india | D35: Service & Spares | E35: Standard | F35: 1500 | G35: 2026-08-18
A36: Triple action baling press: Specifications, Sizing and What to Check Before You Buy | B36: triple action baling press | D36: Balers | E36: Standard | F36: 1500 | G36: 2026-08-19
A37: Hydraulic cylinder for baling press: Specifications, Sizing and What to Check Before You Buy | B37: hydraulic cylinder for baling press | D37: Service & Spares | E37: Standard | F37: 1500 | G37: 2026-08-19
A38: Plastic baling machine: Specifications, Sizing and What to Check Before You Buy | B38: plastic baling machine | D38: Balers | E38: Standard | F38: 1500 | G38: 2026-08-20
... A69: Baling press manufacturer in india: Specifications, Sizing and What to Check Before You Buy | B69: baling press manufacturer in india | D69: Balers | E69: Standard | F69: 1500 | G69: 2026-09-05

Sheet Dashboard
B2: SEO DASHBOARD
B3: Updates automatically from every other sheet.
B5: HEADLINE NUMBERS | E5: BY CATEGORY
B6: Keywords tracked | C6: =COUNTA('Keyword Master'!B5:B269) | E6: Category | F6: Keywords | G6: Est. Vol/mo | H6: Avg Diff | I6: Avg Priority | J6: On Page 1
B7: Total est. monthly volume (India) | C7: =SUM('Keyword Master'!G5:G269) | E7: Balers | F7: =COUNTIF('Keyword Master'!$C$5:$C$269,E7) | G7: =SUMIF('Keyword Master'!$C$5:$C$269,E7,'Keyword Master'!$G$5:$G$269) | H7: =IFERROR(ROUND(AVERAGEIF('Keyword Master'!$C$5:$C$269,E7,'Keyword Master'!$I$5:$I$269),0),"-") | I7: =IFERROR(ROUND(AVERAGEIF('Keyword Master'!$C$5:$C$269,E7,'Keyword Master'!$L$5:$L$269),1),"-") | J7: =COUNTIFS('Rank Tracker'!$C$5:$C$265,E7,'Rank Tracker'!$E$5:$E$265,">0",'Rank Tracker'!$E$5:$E$265,"<=10")
B8: Low-difficulty keywords (<=20) | C8: =COUNTIF('Keyword Master'!I5:I269,"<=20") | E8: ELV / RVSF | F8: =COUNTIF('Keyword Master'!$C$5:$C$269,E8) | G8: =SUMIF('Keyword Master'!$C$5:$C$269,E8,'Keyword Master'!$G$5:$G$269) | H8: =IFERROR(ROUND(AVERAGEIF('Keyword Master'!$C$5:$C$269,E8,'Keyword Master'!$I$5:$I$269),0),"-") | I8: =IFERROR(ROUND(AVERAGEIF('Keyword Master'!$C$5:$C$269,E8,'Keyword Master'!$L$5:$L$269),1),"-") | J8: =COUNTIFS('Rank Tracker'!$C$5:$C$265,E8,'Rank Tracker'!$E$5:$E$265,">0",'Rank Tracker'!$E$5:$E$265,"<=10")
B9: Priority 1 keywords (do now) | C9: =COUNTIF('Keyword Master'!M5:M269,"1 - Do now") | E9: Shears & Nibblers | F9: =COUNTIF('Keyword Master'!$C$5:$C$269,E9) | G9: =SUMIF('Keyword Master'!$C$5:$C$269,E9,'Keyword Master'!$G$5:$G$269) | H9: =IFERROR(ROUND(AVERAGEIF('Keyword Master'!$C$5:$C$269,E9,'Keyword Master'!$I$5:$I$269),0),"-") | I9: =IFERROR(ROUND(AVERAGEIF('Keyword Master'!$C$5:$C$269,E9,'Keyword Master'!$L$5:$L$269),1),"-") | J9: =COUNTIFS('Rank Tracker'!$C$5:$C$265,E9,'Rank Tracker'!$E$5:$E$265,">0",'Rank Tracker'!$E$5:$E$265,"<=10")
B10: Keywords with a position entered | C10: =COUNT('Rank Tracker'!E5:E265) | E10: Shredders & Crackers | F10: =COUNTIF('Keyword Master'!$C$5:$C$269,E10) | G10: =SUMIF('Keyword Master'!$C$5:$C$269,E10,'Keyword Master'!$G$5:$G$269) | H10: =IFERROR(ROUND(AVERAGEIF('Keyword Master'!$C$5:$C$269,E10,'Keyword Master'!$I$5:$I$269),0),"-") | I10: =IFERROR(ROUND(AVERAGEIF('Keyword Master'!$C$5:$C$269,E10,'Keyword Master'!$L$5:$L$269),1),"-") | J10: =COUNTIFS('Rank Tracker'!$C$5:$C$265,E10,'Rank Tracker'!$E$5:$E$265,">0",'Rank Tracker'!$E$5:$E$265,"<=10")
B11: Ranking in top 3 | C11: =COUNTIFS('Rank Tracker'!E5:E265,">0",'Rank Tracker'!E5:E265,"<=3") | E11: Briquetting | F11: =COUNTIF('Keyword Master'!$C$5:$C$269,E11) | G11: =SUMIF('Keyword Master'!$C$5:$C$269,E11,'Keyword Master'!$G$5:$G$269) | H11: =IFERROR(ROUND(AVERAGEIF('Keyword Master'!$C$5:$C$269,E11,'Keyword Master'!$I$5:$I$269),0),"-") | I11: =IFERROR(ROUND(AVERAGEIF('Keyword Master'!$C$5:$C$269,E11,'Keyword Master'!$L$5:$L$269),1),"-") | J11: =COUNTIFS('Rank Tracker'!$C$5:$C$265,E11,'Rank Tracker'!$E$5:$E$265,">0",'Rank Tracker'!$E$5:$E$265,"<=10")
B12: Ranking on page 1 (top 10) | C12: =COUNTIFS('Rank Tracker'!E5:E265,">0",'Rank Tracker'!E5:E265,"<=10") | E12: Material Handling | F12: =COUNTIF('Keyword Master'!$C$5:$C$269,E12) | G12: =SUMIF('Keyword Master'!$C$5:$C$269,E12,'Keyword Master'!$G$5:$G$269) | H12: =IFERROR(ROUND(AVERAGEIF('Keyword Master'!$C$5:$C$269,E12,'Keyword Master'!$I$5:$I$269),0),"-") | I12: =IFERROR(ROUND(AVERAGEIF('Keyword Master'!$C$5:$C$269,E12,'Keyword Master'!$L$5:$L$269),1),"-") | J12: =COUNTIFS('Rank Tracker'!$C$5:$C$265,E12,'Rank Tracker'!$E$5:$E$265,">0",'Rank Tracker'!$E$5:$E$265,"<=10")
B13: Near wins (position 11-20) | C13: =COUNTIFS('Rank Tracker'!E5:E265,">10",'Rank Tracker'!E5:E265,"<=20") | E13: Agriculture | F13: =COUNTIF('Keyword Master'!$C$5:$C$269,E13) | G13: =SUMIF('Keyword Master'!$C$5:$C$269,E13,'Keyword Master'!$G$5:$G$269) | H13: =IFERROR(ROUND(AVERAGEIF('Keyword Master'!$C$5:$C$269,E13,'Keyword Master'!$I$5:$I$269),0),"-") | I13: =IFERROR(ROUND(AVERAGEIF('Keyword Master'!$C$5:$C$269,E13,'Keyword Master'!$L$5:$L$269),1),"-") | J13: =COUNTIFS('Rank Tracker'!$C$5:$C$265,E13,'Rank Tracker'!$E$5:$E$265,">0",'Rank Tracker'!$E$5:$E$265,"<=10")
B14: Average position (tracked only) | C14: =IFERROR(AVERAGEIF('Rank Tracker'!E5:E265,">0"),"-") | E14: Service & Spares | F14: =COUNTIF('Keyword Master'!$C$5:$C$269,E14) | G14: =SUMIF('Keyword Master'!$C$5:$C$269,E14,'Keyword Master'!$G$5:$G$269) | H14: =IFERROR(ROUND(AVERAGEIF('Keyword Master'!$C$5:$C$269,E14,'Keyword Master'!$I$5:$I$269),0),"-") | I14: =IFERROR(ROUND(AVERAGEIF('Keyword Master'!$C$5:$C$269,E14,'Keyword Master'!$L$5:$L$269),1),"-") | J14: =COUNTIFS('Rank Tracker'!$C$5:$C$265,E14,'Rank Tracker'!$E$5:$E$265,">0",'Rank Tracker'!$E$5:$E$265,"<=10")
B15: Keywords improved vs baseline | C15: =COUNTIF('Rank Tracker'!H5:H265,">0") | E15: Informational | F15: =COUNTIF('Keyword Master'!$C$5:$C$269,E15) | G15: =SUMIF('Keyword Master'!$C$5:$C$269,E15,'Keyword Master'!$G$5:$G$269) | H15: =IFERROR(ROUND(AVERAGEIF('Keyword Master'!$C$5:$C$269,E15,'Keyword Master'!$I$5:$I$269),0),"-") | I15: =IFERROR(ROUND(AVERAGEIF('Keyword Master'!$C$5:$C$269,E15,'Keyword Master'!$L$5:$L$269),1),"-") | J15: =COUNTIFS('Rank Tracker'!$C$5:$C$265,E15,'Rank Tracker'!$E$5:$E$265,">0",'Rank Tracker'!$E$5:$E$265,"<=10")
B16: Competitors audited | C16: =COUNTA('Competitor Audit'!A5:A17) | E16: Thought Leadership | F16: =COUNTIF('Keyword Master'!$C$5:$C$269,E16) | G16: =SUMIF('Keyword Master'!$C$5:$C$269,E16,'Keyword Master'!$G$5:$G$269) | H16: =IFERROR(ROUND(AVERAGEIF('Keyword Master'!$C$5:$C$269,E16,'Keyword Master'!$I$5:$I$269),0),"-") | I16: =IFERROR(ROUND(AVERAGEIF('Keyword Master'!$C$5:$C$269,E16,'Keyword Master'!$L$5:$L$269),1),"-") | J16: =COUNTIFS('Rank Tracker'!$C$5:$C$265,E16,'Rank Tracker'!$E$5:$E$265,">0",'Rank Tracker'!$E$5:$E$265,"<=10")
B17: Competitors with an owned site + blog | C17: =COUNTIFS('Competitor Audit'!D5:D17,"Yes",'Competitor Audit'!E5:E17,"Yes") | E17: Industry Verticals | F17: =COUNTIF('Keyword Master'!$C$5:$C$269,E17) | G17: =SUMIF('Keyword Master'!$C$5:$C$269,E17,'Keyword Master'!$G$5:$G$269) | H17: =IFERROR(ROUND(AVERAGEIF('Keyword Master'!$C$5:$C$269,E17,'Keyword Master'!$I$5:$I$269),0),"-") | I17: =IFERROR(ROUND(AVERAGEIF('Keyword Master'!$C$5:$C$269,E17,'Keyword Master'!$L$5:$L$269),1),"-") | J17: =COUNTIFS('Rank Tracker'!$C$5:$C$265,E17,'Rank Tracker'!$E$5:$E$265,">0",'Rank Tracker'!$E$5:$E$265,"<=10")
B18: Content gaps identified | C18: =COUNTA('Content Gaps'!A5:A16) | E18: Local SEO | F18: =COUNTIF('Keyword Master'!$C$5:$C$269,E18) | G18: =SUMIF('Keyword Master'!$C$5:$C$269,E18,'Keyword Master'!$G$5:$G$269) | H18: =IFERROR(ROUND(AVERAGEIF('Keyword Master'!$C$5:$C$269,E18,'Keyword Master'!$I$5:$I$269),0),"-") | I18: =IFERROR(ROUND(AVERAGEIF('Keyword Master'!$C$5:$C$269,E18,'Keyword Master'!$L$5:$L$269),1),"-") | J18: =COUNTIFS('Rank Tracker'!$C$5:$C$265,E18,'Rank Tracker'!$E$5:$E$265,">0",'Rank Tracker'!$E$5:$E$265,"<=10")
B19: Blogs in pipeline | C19: =COUNTA('Blog Pipeline'!F5:F69) | E19: Export | F19: =COUNTIF('Keyword Master'!$C$5:$C$269,E19) | G19: =SUMIF('Keyword Master'!$C$5:$C$269,E19,'Keyword Master'!$G$5:$G$269) | H19: =IFERROR(ROUND(AVERAGEIF('Keyword Master'!$C$5:$C$269,E19,'Keyword Master'!$I$5:$I$269),0),"-") | I19: =IFERROR(ROUND(AVERAGEIF('Keyword Master'!$C$5:$C$269,E19,'Keyword Master'!$L$5:$L$269),1),"-") | J19: =COUNTIFS('Rank Tracker'!$C$5:$C$265,E19,'Rank Tracker'!$E$5:$E$265,">0",'Rank Tracker'!$E$5:$E$265,"<=10")
B20: Blogs written | C20: =COUNTIF('Blog Pipeline'!L5:L69,"YES") | E20: Long-tail Questions | F20: =COUNTIF('Keyword Master'!$C$5:$C$269,E20) | G20: =SUMIF('Keyword Master'!$C$5:$C$269,E20,'Keyword Master'!$G$5:$G$269) | H20: =IFERROR(ROUND(AVERAGEIF('Keyword Master'!$C$5:$C$269,E20,'Keyword Master'!$I$5:$I$269),0),"-") | I20: =IFERROR(ROUND(AVERAGEIF('Keyword Master'!$C$5:$C$269,E20,'Keyword Master'!$L$5:$L$269),1),"-") | J20: =COUNTIFS('Rank Tracker'!$C$5:$C$265,E20,'Rank Tracker'!$E$5:$E$265,">0",'Rank Tracker'!$E$5:$E$265,"<=10")
B21: Blogs published | C21: =COUNTIF('Content Map'!I5:I69,"Published") | E21: TOTAL | F21: =SUM(F7:F20) | G21: =SUM(G7:G20) | J21: =SUM(J7:J20)
B22: Total clicks logged | C22: ='Traffic & Conversions'!E157
B23: Total enquiries logged | C23: ='Traffic & Conversions'!H157
B24: Overall enquiry rate | C24: =IFERROR('Traffic & Conversions'!H157/'Traffic & Conversions'!E157,0)
B26: ⚠ Rank data will stay empty until JHP has an owned website. See README and the SEO Strategy document.
